README.md
setup.py
cerespacketexploder/__init__.py
cerespacketexploder/api.py
cerespacketexploder/core.py
cerespacketexploder/observable.py
cerespacketexploder/utils.py
cerespacketexploder.egg-info/PKG-INFO
cerespacketexploder.egg-info/SOURCES.txt
cerespacketexploder.egg-info/dependency_links.txt
cerespacketexploder.egg-info/requires.txt
cerespacketexploder.egg-info/top_level.txt
cerespacketexploder/parser/__init__.py
cerespacketexploder/parser/http.py
cerespacketexploder/parser/parser.py