Metadata-Version: 1.2
Name: cerespacketexploder
Version: 2.0.0
Summary: Python library for extracting observables from pcap.
Home-page: https://github.com/Cyberprotect/Ceres-Packet-Exploder
Author: Rémi ALLAIN
Author-email: rallain@cyberprotect.fr
Maintainer: Rémi ALLAIN
License: Apache 2.0
Platform: UNKNOWN
Classifier: Intended Audience :: Developers
Classifier: Intended Audience :: Information Technology
Classifier: Intended Audience :: Science/Research
Classifier: Natural Language :: English
Classifier: Operating System :: OS Independent
Classifier: Programming Language :: Python
Classifier: Topic :: Security
Classifier: Topic :: Software Development :: Libraries :: Python Modules
